ovos_classifiers/__init__.py
ovos_classifiers/corefiob.py
ovos_classifiers/postag.py
ovos_classifiers/utttags.py
ovos_classifiers/version.py
ovos_classifiers/datasets/__init__.py
ovos_classifiers/datasets/tagsets.py
ovos_classifiers/datasets/wordnet.py
ovos_classifiers/heuristics/__init__.py
ovos_classifiers/heuristics/corefiob.py
ovos_classifiers/heuristics/inflection.py
ovos_classifiers/heuristics/keyword_extraction.py
ovos_classifiers/heuristics/lang_detect.py
ovos_classifiers/heuristics/machine_comprehension.py
ovos_classifiers/heuristics/normalize.py
ovos_classifiers/heuristics/numeric.py
ovos_classifiers/heuristics/phonemizer.py
ovos_classifiers/heuristics/postag.py
ovos_classifiers/heuristics/summarization.py
ovos_classifiers/heuristics/time.py
ovos_classifiers/heuristics/tokenize.py
ovos_classifiers/heuristics/utttags.py
ovos_classifiers/opm/__init__.py
ovos_classifiers/opm/heuristics.py
ovos_classifiers/opm/nltk.py
ovos_classifiers/res/az/normalize.json
ovos_classifiers/res/ca/corefiob.json
ovos_classifiers/res/ca/normalize.json
ovos_classifiers/res/cz/normalize.json
ovos_classifiers/res/de/corefiob.json
ovos_classifiers/res/de/normalize.json
ovos_classifiers/res/de/utttags.json
ovos_classifiers/res/en/corefiob.json
ovos_classifiers/res/en/normalize.json
ovos_classifiers/res/en/pluralizations.json
ovos_classifiers/res/en/utttags.json
ovos_classifiers/res/es/corefiob.json
ovos_classifiers/res/es/normalize.json
ovos_classifiers/res/es/utttags.json
ovos_classifiers/res/fr/corefiob.json
ovos_classifiers/res/fr/normalize.json
ovos_classifiers/res/fr/utttags.json
ovos_classifiers/res/it/corefiob.json
ovos_classifiers/res/it/normalize.json
ovos_classifiers/res/it/utttags.json
ovos_classifiers/res/nl/corefiob.json
ovos_classifiers/res/nl/normalize.json
ovos_classifiers/res/nl/utttags.json
ovos_classifiers/res/no/normalize.json
ovos_classifiers/res/no/utttags.json
ovos_classifiers/res/pt/corefiob.json
ovos_classifiers/res/pt/normalize.json
ovos_classifiers-0.0.0a58.dist-info/LICENSE
ovos_classifiers-0.0.0a58.dist-info/METADATA
ovos_classifiers-0.0.0a58.dist-info/WHEEL
ovos_classifiers-0.0.0a58.dist-info/entry_points.txt
ovos_classifiers-0.0.0a58.dist-info/top_level.txt
ovos_classifiers-0.0.0a58.dist-info/zip-safe
ovos_classifiers-0.0.0a58.dist-info/RECORD
